pyaffine/__init__.py
pyaffine/main.py
pyaffine-0.2.0.dist-info/entry_points.txt
pyaffine-0.2.0.dist-info/WHEEL
pyaffine-0.2.0.dist-info/METADATA
pyaffine-0.2.0.dist-info/RECORD
